{
    "tweet_id": "2022_train_main_tweet_29",
    "tweet": "Never forget what he taught us.\nNever let the spirit of Godse win. @URL",
    "comments": [
        {
            "tweet_id": "2022_train_main_tweet_29_comment_1",
            "tweet": "@AUTHOR Vir he himself would've forgiven Godse. Infact his own son had offered to defend Godse. Godse is not the right man to remember today. Today is not Gandhi punyatithi.",
            "replies": [
                {
                    "tweet_id": "2022_train_main_tweet_29_comment_1_reply_1",
                    "tweet": "@COMMENTATOR @AUTHOR Vir trying to increase his TRP\nStandard operatice practice"
                },
                {
                    "tweet_id": "2022_train_main_tweet_29_comment_1_reply_2",
                    "tweet": "@COMMENTATOR @AUTHOR Thank you for putting out this fact. People who chose to highlight Godse today have a shallow understanding of life &amp; death - expecting them to understand much is completely useless. May their own souls find peace after death."
                }
            ]
        },
        {
            "tweet_id": "2022_train_main_tweet_29_comment_2",
            "tweet": "@AUTHOR Sometimes i wonder if he was alive when Ajmal Kasab was caught ..he would begin his fast to force govt to release Kasab ..",
            "replies": [
                {
                    "tweet_id": "2022_train_main_tweet_29_comment_2_reply_1",
                    "tweet": "@COMMENTATOR @AUTHOR Much like Mr. Hazare."
                }
            ]
        },
        {
            "tweet_id": "2022_train_main_tweet_29_comment_3",
            "tweet": "@AUTHOR The rise in spirit of Godse winning or losing depends upon the appeasement politics of pseudo seculars parties.Gandhi taughts were never towards appeasement politics or hindutuva politics.Eshwar Allah thero naam sabko sanmathi de bhagwan🙏",
            "replies": [
                {
                    "tweet_id": "2022_train_main_tweet_29_comment_3_reply_1",
                    "tweet": "@COMMENTATOR @AUTHOR Want to say something??\n@URL"
                },
                {
                    "tweet_id": "2022_train_main_tweet_29_comment_3_reply_2",
                    "tweet": "@COMMENTATOR @AUTHOR Pls read abt the Moplah Massacre. Gandhi was more than evil personified than those evil Muslims who massacred harmless Hindus."
                },
                {
                    "tweet_id": "2022_train_main_tweet_29_comment_3_reply_3",
                    "tweet": "@COMMENTATOR @AUTHOR RSS/BJP peddle word \" appeasement\" for political gain and electrol win and were very successful in it. However what is very unfortunate is that bhakts still don't understand that it is nothing but to create hate against muslim. This appeasement word never been used against any"
                },
                {
                    "tweet_id": "2022_train_main_tweet_29_comment_3_reply_4",
                    "tweet": "@COMMENTATOR @AUTHOR Other community, caste or class of people despite there been many so called appeasement policies and favour accorded to them. This word is reseved for only muslim. Though even after 75 yrs of independance they remain most backward community in india"
                }
            ]
        },
        {
            "tweet_id": "2022_train_main_tweet_29_comment_4",
            "tweet": "@AUTHOR Sir I fell we need to think of if the box as rational mind.I praise Gandiji but I also feel he is been provided more lime light then should have got.\nThere were many freedom fighters who did great on ground and lost in dust as apart from locals no were its been found \n@USER",
            "replies": [
                {
                    "tweet_id": "2022_train_main_tweet_29_comment_4_reply_1",
                    "tweet": "@COMMENTATOR @AUTHOR @USER Unfortunately we have this knack/habit of either putting people on pedestals and making them gods or putting them down and trampling them. There's never a mid way that is rational or sensible.\nWe can't accept that idols also have negative points."
                }
            ]
        },
        {
            "tweet_id": "2022_train_main_tweet_29_comment_5",
            "tweet": "@AUTHOR #Gandhi @URL",
            "replies": [
                {
                    "tweet_id": "2022_train_main_tweet_29_comment_5_reply_1",
                    "tweet": "@COMMENTATOR @AUTHOR It’s like saying in the battle between the 9/11 victims and Osama bin laden , I stand with the 9/11 victims 😂. Please don’t glorify that name."
                },
                {
                    "tweet_id": "2022_train_main_tweet_29_comment_5_reply_2",
                    "tweet": "@COMMENTATOR @AUTHOR Lwda"
                }
            ]
        },
        {
            "tweet_id": "2022_train_main_tweet_29_comment_6",
            "tweet": "@AUTHOR One person @USER single handedly takes them ( RSS) on.\nPeople like you criticize and make him irrelevant in the name of journalism and most of the journalists openly support the government tilting the balance in favour of what you want not to win.",
            "replies": [
                {
                    "tweet_id": "2022_train_main_tweet_29_comment_6_reply_1",
                    "tweet": "@COMMENTATOR @AUTHOR @USER 😂 😂 😂 😂 😂"
                }
            ]
        },
        {
            "tweet_id": "2022_train_main_tweet_29_comment_7",
            "tweet": "@AUTHOR Godse Zindabaad is trending at no 2 in India it seems the sanghi communal forces along with godi media will destroy my country \nSecular forces seem to be weakened by infighting \nJust hope 2024 sees a new dawn otherwise we are doomed \n#GodseMurdabaad",
            "replies": [
                {
                    "tweet_id": "2022_train_main_tweet_29_comment_7_reply_1",
                    "tweet": "@COMMENTATOR @AUTHOR 😂😂😂😂\nYou Anti Nationals cry when Terrorists are encountered in batla house.\n\nYou Traitors support Tukde Tukde Gang\n\nYou Radicals tried to save 26/11 Terrorists by blaming the attack on hindus/rss &amp; published book 26/11 rss ki sazis.\n\nAnd Yet YOU blame sanghi 😂😂"
                }
            ]
        },
        {
            "tweet_id": "2022_train_main_tweet_29_comment_8",
            "tweet": "@AUTHOR I don’t think this kind of # acceptable. Everyone should respect Gandhiji contribution to toward nation as well human being",
            "replies": [
                {
                    "tweet_id": "2022_train_main_tweet_29_comment_8_reply_1",
                    "tweet": "@COMMENTATOR @AUTHOR Respect is earned not demanded."
                }
            ]
        },
        {
            "tweet_id": "2022_train_main_tweet_29_comment_9",
            "tweet": "@AUTHOR Nathuram Godse Amar Rahe, baki chamche LOL😁😁😁",
            "replies": [
                {
                    "tweet_id": "2022_train_main_tweet_29_comment_9_reply_1",
                    "tweet": "@COMMENTATOR Sanghi scum"
                }
            ]
        },
        {
            "tweet_id": "2022_train_main_tweet_29_comment_10",
            "tweet": "@AUTHOR @USER True never forget he was the father of partition....",
            "replies": [
                {
                    "tweet_id": "2022_train_main_tweet_29_comment_10_reply_1",
                    "tweet": "@COMMENTATOR @AUTHOR @USER and murderer of 2 lakh innocent Hindu ."
                }
            ]
        },
        {
            "tweet_id": "2022_train_main_tweet_29_comment_11",
            "tweet": "@AUTHOR He taught Muzlim Appeasement, no question of forgetting…..",
            "replies": [
                {
                    "tweet_id": "2022_train_main_tweet_29_comment_11_reply_1",
                    "tweet": "@COMMENTATOR Sanghi scum"
                }
            ]
        }
    ]
}