{
    "tweet_id": "2021_train_main_tweet_52",
    "tweet": "Ok but liberals are not ‘anti-Hindu’ ..",
    "comments": [
        {
            "tweet_id": "2021_train_main_tweet_52_comment_1",
            "tweet": "@AUTHOR Then who? your father's rite \n🐖 Thinking like 🐷🐷🐷🐷",
            "replies": [
                {
                    "tweet_id": "2021_train_main_tweet_52_comment_1_reply_1",
                    "tweet": "@COMMENTATOR @AUTHOR Bhai aaram se i also don't like her but her father is a retired navy officer (commodore) @USER"
                },
                {
                    "tweet_id": "2021_train_main_tweet_52_comment_1_reply_2",
                    "tweet": "@COMMENTATOR @AUTHOR 😂😂😂👍"
                }
            ]
        },
        {
            "tweet_id": "2021_train_main_tweet_52_comment_2",
            "tweet": "@AUTHOR Surely BHIMTAA are anti Hindu",
            "replies": [
                {
                    "tweet_id": "2021_train_main_tweet_52_comment_2_reply_1",
                    "tweet": "@COMMENTATOR @AUTHOR Using slurs is the easiest thing that comes naturally to right wing bigots."
                }
            ]
        },
        {
            "tweet_id": "2021_train_main_tweet_52_comment_3",
            "tweet": "@AUTHOR But you don't like Hindu &amp; RSS man. Your tweets refer in this regard."
        },
        {
            "tweet_id": "2021_train_main_tweet_52_comment_4",
            "tweet": "@AUTHOR 3-1%% लिखने में कितना अच्छा लगता है कांग्रेस को \n\n20 करोड़ लिखने में  शर्म आती है..\n\nनिर्लज्ज कांग्रेस.."
        },
        {
            "tweet_id": "2021_train_main_tweet_52_comment_5",
            "tweet": "@AUTHOR But that's an easier option tag us as anti-Hindu for the bhakts. Neednt be logically backed",
            "replies": [
                {
                    "tweet_id": "2021_train_main_tweet_52_comment_5_reply_1",
                    "tweet": "@COMMENTATOR @AUTHOR Like people tag every one as \"fascists\". No logic either.."
                },
                {
                    "tweet_id": "2021_train_main_tweet_52_comment_5_reply_2",
                    "tweet": "@COMMENTATOR @AUTHOR @COMMENTATOR Auntyji ek glass wine pi ke soo jao.."
                },
                {
                    "tweet_id": "2021_train_main_tweet_52_comment_5_reply_3",
                    "tweet": "@COMMENTATOR @AUTHOR liberals and logic are 2 parallel lines."
                },
                {
                    "tweet_id": "2021_train_main_tweet_52_comment_5_reply_4",
                    "tweet": "@COMMENTATOR @AUTHOR Do you support liberal economy?"
                },
                {
                    "tweet_id": "2021_train_main_tweet_52_comment_5_reply_5",
                    "tweet": "@COMMENTATOR @AUTHOR Not the Bhakts lol🤣 liberals are anyways against the majorities! Speaking facts doesn't come to your mind!!"
                },
                {
                    "tweet_id": "2021_train_main_tweet_52_comment_5_reply_6",
                    "tweet": "@COMMENTATOR @AUTHOR Shut up sewer rat sharmistha"
                }
            ]
        },
        {
            "tweet_id": "2021_train_main_tweet_52_comment_6",
            "tweet": "@AUTHOR They are \nAnd you are"
        },
        {
            "tweet_id": "2021_train_main_tweet_52_comment_7",
            "tweet": "@AUTHOR Yes they are"
        },
        {
            "tweet_id": "2021_train_main_tweet_52_comment_8",
            "tweet": "@AUTHOR but you are liberal."
        },
        {
            "tweet_id": "2021_train_main_tweet_52_comment_9",
            "tweet": "@AUTHOR Yes thet are anti India"
        },
        {
            "tweet_id": "2021_train_main_tweet_52_comment_10",
            "tweet": "@AUTHOR Who the hell are you?",
            "replies": [
                {
                    "tweet_id": "2021_train_main_tweet_52_comment_10_reply_1",
                    "tweet": "@COMMENTATOR @AUTHOR She is c-grade actress in bollywood.🤣"
                }
            ]
        },
        {
            "tweet_id": "2021_train_main_tweet_52_comment_11",
            "tweet": "@AUTHOR It means Liberals supports \"Caste System\"\n'Hidden Brahmanism in the name of Liberalism and Feminism'"
        },
        {
            "tweet_id": "2021_train_main_tweet_52_comment_12",
            "tweet": "@AUTHOR देश के गद्दारो को\nगोली मारो सालो को\nये सुनकर एक खास किस्म बिलबिला उठती है।\nपता नहीं क्यो?"
        },
        {
            "tweet_id": "2021_train_main_tweet_52_comment_13",
            "tweet": "@AUTHOR How do u define anti-Hindu? It need not be hate for Hindus. It can just be denial of injustice to Hindus. You raise Akhlaq/Pehlu/Junaid, rightly so but ignore Bharat Yadav/Sawan Rathod/Purnia Dalits/Lotan Nishad etc. killed by Muslim mobs. That is anti-Hinduism. Simple.",
            "replies": [
                {
                    "tweet_id": "2021_train_main_tweet_52_comment_13_reply_1",
                    "tweet": "@AUTHOR You declare 2012 Mumbai riots by huge Muslim mob as fake. Police Men were beaten &amp; Police women were molested. You call it fake. That is indeed being anti-Hindu. Simple."
                },
                {
                    "tweet_id": "2021_train_main_tweet_52_comment_13_reply_2",
                    "tweet": "@COMMENTATOR @AUTHOR Correction \"killed by hindu mob\"........not by muslim"
                }
            ]
        },
        {
            "tweet_id": "2021_train_main_tweet_52_comment_14",
            "tweet": "@AUTHOR But you are"
        },
        {
            "tweet_id": "2021_train_main_tweet_52_comment_15",
            "tweet": "@AUTHOR What about negative liberals like swara."
        },
        {
            "tweet_id": "2021_train_main_tweet_52_comment_16",
            "tweet": "@AUTHOR Lol"
        },
        {
            "tweet_id": "2021_train_main_tweet_52_comment_17",
            "tweet": "@AUTHOR Madam they are not anti,they are enemies of Hindu@@@@@"
        },
        {
            "tweet_id": "2021_train_main_tweet_52_comment_18",
            "tweet": "@AUTHOR हनुमान चालीसा,, सुनाओ।"
        },
        {
            "tweet_id": "2021_train_main_tweet_52_comment_19",
            "tweet": "@AUTHOR Nice to hear swara."
        },
        {
            "tweet_id": "2021_train_main_tweet_52_comment_20",
            "tweet": "@AUTHOR What a joke!"
        },
        {
            "tweet_id": "2021_train_main_tweet_52_comment_21",
            "tweet": "@AUTHOR They are anti-national, and #Hindu is our nationality"
        },
        {
            "tweet_id": "2021_train_main_tweet_52_comment_22",
            "tweet": "@AUTHOR True... They are skull cap lovers",
            "replies": [
                {
                    "tweet_id": "2021_train_main_tweet_52_comment_22_reply_1",
                    "tweet": "@COMMENTATOR @AUTHOR True🤟"
                }
            ]
        },
        {
            "tweet_id": "2021_train_main_tweet_52_comment_23",
            "tweet": "@AUTHOR But you are!"
        },
        {
            "tweet_id": "2021_train_main_tweet_52_comment_24",
            "tweet": "@AUTHOR आन्टी जी कुछ समझ भी आया है या बस ऐसे ही 😂😂"
        },
        {
            "tweet_id": "2021_train_main_tweet_52_comment_25",
            "tweet": "@AUTHOR I love kejri... But this kind of politics i hate.     #  ..  vote ka chakkar babu bhaiya :)   yogi ji never did this kind of politics .. @URL"
        },
        {
            "tweet_id": "2021_train_main_tweet_52_comment_26",
            "tweet": "@AUTHOR Come on aunty, ye bolnse nahi hoga kuch."
        },
        {
            "tweet_id": "2021_train_main_tweet_52_comment_27",
            "tweet": "@AUTHOR Yes true. Liberals are not anti-Hindi, they are anti-India."
        },
        {
            "tweet_id": "2021_train_main_tweet_52_comment_28",
            "tweet": "@AUTHOR रोजगार के लिए apply कर दो tweeter बन्द होने wala hai. Gog wale ko bata do is bar 400ke par. All members of tukde tukde gand are anti iindia and Hindu",
            "replies": [
                {
                    "tweet_id": "2021_train_main_tweet_52_comment_28_reply_1",
                    "tweet": "@COMMENTATOR @AUTHOR She has rojgaar \n\nFor promoting pakistani vibrator"
                }
            ]
        },
        {
            "tweet_id": "2021_train_main_tweet_52_comment_29",
            "tweet": "@AUTHOR Yeah Swara you are right for the first time you are not anti-Hindu because you are not even a Hindu."
        },
        {
            "tweet_id": "2021_train_main_tweet_52_comment_30",
            "tweet": "@AUTHOR But you are !"
        },
        {
            "tweet_id": "2021_train_main_tweet_52_comment_31",
            "tweet": "@AUTHOR Liberals favour Muslims \nLiberals feel ashamed being Hindu\nLiberals mock RSS\nBut Liberals aren't 'anti hindu'.\nLet that sink in."
        },
        {
            "tweet_id": "2021_train_main_tweet_52_comment_32",
            "tweet": "@AUTHOR Can u pl say something on this? @URL"
        },
        {
            "tweet_id": "2021_train_main_tweet_52_comment_33",
            "tweet": "@AUTHOR They are anti hindu and anti india too\n\n#FO"
        },
        {
            "tweet_id": "2021_train_main_tweet_52_comment_34",
            "tweet": "@AUTHOR The luxury of privilege"
        },
        {
            "tweet_id": "2021_train_main_tweet_52_comment_35",
            "tweet": "@AUTHOR Okay. Aap bol rahe ho to thik hi hoga."
        },
        {
            "tweet_id": "2021_train_main_tweet_52_comment_36",
            "tweet": "@AUTHOR Tum mam sab Sai badi ANTI-HINDU ho"
        },
        {
            "tweet_id": "2021_train_main_tweet_52_comment_37",
            "tweet": "@AUTHOR #भारत की तरह ही #CAA कानून #पाकिस्तान को भी लागू करना चाहिए ताकि जिन्हे पाकिस्तान पसंद है वह वहां जाकर रह सके\n#जय_हिंद 🙏"
        },
        {
            "tweet_id": "2021_train_main_tweet_52_comment_38",
            "tweet": "@AUTHOR Anti-CAA = Anti-Hindu\n#AntiCAAisAntiHindu"
        },
        {
            "tweet_id": "2021_train_main_tweet_52_comment_39",
            "tweet": "@AUTHOR Nopes who says Librandus r anti hindus ? Mam pls can i DM u have to tell u something very important about RSS goons . Only if u say yes i will DM but its really urgent mam . #HumLeKRahengeAzadi",
            "replies": [
                {
                    "tweet_id": "2021_train_main_tweet_52_comment_39_reply_1",
                    "tweet": "@COMMENTATOR @AUTHOR Try to DM me"
                },
                {
                    "tweet_id": "2021_train_main_tweet_52_comment_39_reply_2",
                    "tweet": "@COMMENTATOR @AUTHOR Abe khud Ka account nakli naam se hai aur RSS ko goons BATA rahe hai .."
                }
            ]
        },
        {
            "tweet_id": "2021_train_main_tweet_52_comment_40",
            "tweet": "@AUTHOR Liberals just oppose Article 370,CAA, construction of Ram Mandir, UCC"
        },
        {
            "tweet_id": "2021_train_main_tweet_52_comment_41",
            "tweet": "@AUTHOR You guys are ."
        },
        {
            "tweet_id": "2021_train_main_tweet_52_comment_42",
            "tweet": "@AUTHOR When someone says that they have problems with liberals, then that’s the problem"
        },
        {
            "tweet_id": "2021_train_main_tweet_52_comment_43",
            "tweet": "@AUTHOR You are not only anti Hindu , you are antinational"
        },
        {
            "tweet_id": "2021_train_main_tweet_52_comment_44",
            "tweet": "@AUTHOR But #aunty is anty india"
        },
        {
            "tweet_id": "2021_train_main_tweet_52_comment_45",
            "tweet": "@AUTHOR 2 kaudi ki actress akkk thoo"
        },
        {
            "tweet_id": "2021_train_main_tweet_52_comment_46",
            "tweet": "@AUTHOR Jhut bolne wala agar swayam ko saccha kahe to kya maan lena chahiye?"
        },
        {
            "tweet_id": "2021_train_main_tweet_52_comment_47",
            "tweet": "@AUTHOR Imao"
        },
        {
            "tweet_id": "2021_train_main_tweet_52_comment_48",
            "tweet": "@AUTHOR But they are pro muslim too.."
        },
        {
            "tweet_id": "2021_train_main_tweet_52_comment_49",
            "tweet": "@AUTHOR Who is this comedian calling self as libertarian...!"
        },
        {
            "tweet_id": "2021_train_main_tweet_52_comment_50",
            "tweet": "@AUTHOR Mujhe aapki lojik vali baten pasand he or bhakto ko nahi gadha kya jane adrak ka sabad",
            "replies": [
                {
                    "tweet_id": "2021_train_main_tweet_52_comment_50_reply_1",
                    "tweet": "@COMMENTATOR @AUTHOR Gaddar kya jaane desh bhakti ka jazba???"
                }
            ]
        },
        {
            "tweet_id": "2021_train_main_tweet_52_comment_51",
            "tweet": "@AUTHOR Librandus from JNU are sure Anti Hindu."
        },
        {
            "tweet_id": "2021_train_main_tweet_52_comment_52",
            "tweet": "@AUTHOR But they are definitely Pro-Muslim"
        },
        {
            "tweet_id": "2021_train_main_tweet_52_comment_53",
            "tweet": "@AUTHOR Of course you are"
        },
        {
            "tweet_id": "2021_train_main_tweet_52_comment_54",
            "tweet": "@AUTHOR They do say so but andar kuch alag hi chal raha hai"
        },
        {
            "tweet_id": "2021_train_main_tweet_52_comment_55",
            "tweet": "@AUTHOR Love the way you lie.😁"
        },
        {
            "tweet_id": "2021_train_main_tweet_52_comment_56",
            "tweet": "@AUTHOR Blue tick shows she is @AUTHOR"
        },
        {
            "tweet_id": "2021_train_main_tweet_52_comment_57",
            "tweet": "@AUTHOR Please, you come in koo app 😀😀😀 \nBut It's impossible because ☺️☺️☺️"
        },
        {
            "tweet_id": "2021_train_main_tweet_52_comment_58",
            "tweet": "@AUTHOR Tell me one statement from certified liberal which is Pro Hindu."
        },
        {
            "tweet_id": "2021_train_main_tweet_52_comment_59",
            "tweet": "@AUTHOR Yes. You are"
        },
        {
            "tweet_id": "2021_train_main_tweet_52_comment_60",
            "tweet": "@AUTHOR But you are... and you are desh Dro hee as well beach",
            "replies": [
                {
                    "tweet_id": "2021_train_main_tweet_52_comment_60_reply_1",
                    "tweet": "@COMMENTATOR @AUTHOR She is KatV desguised by a different name"
                }
            ]
        },
        {
            "tweet_id": "2021_train_main_tweet_52_comment_61",
            "tweet": "@AUTHOR Give me one example"
        },
        {
            "tweet_id": "2021_train_main_tweet_52_comment_62",
            "tweet": "@AUTHOR Yea.. they just despise'em !"
        },
        {
            "tweet_id": "2021_train_main_tweet_52_comment_63",
            "tweet": "@AUTHOR Liberals are Anti Hindu, Anti India, Anti Indian culture, n yes love to tarnish image of this country in every possible manner..\nBas"
        },
        {
            "tweet_id": "2021_train_main_tweet_52_comment_64",
            "tweet": "@AUTHOR But you're anti hindu"
        },
        {
            "tweet_id": "2021_train_main_tweet_52_comment_65",
            "tweet": "@AUTHOR So they are anti national ?????"
        },
        {
            "tweet_id": "2021_train_main_tweet_52_comment_66",
            "tweet": "@AUTHOR Yes they are pro Pakistani 😉😉"
        },
        {
            "tweet_id": "2021_train_main_tweet_52_comment_67",
            "tweet": "@AUTHOR Thieves say I'm not thief🤦"
        },
        {
            "tweet_id": "2021_train_main_tweet_52_comment_68",
            "tweet": "@AUTHOR Liberals are C..."
        },
        {
            "tweet_id": "2021_train_main_tweet_52_comment_69",
            "tweet": "@AUTHOR Pagal swara didi tum to bolo hi mat nahi anty hindu nahi hindu samarthak shut up itna hi hai to baki kisi Dharm ke bareme tweet kar na himmat hongi to nhi to shut up ok na"
        },
        {
            "tweet_id": "2021_train_main_tweet_52_comment_70",
            "tweet": "@AUTHOR Who said you're hindu? \nYou're just a pig of Bollywood"
        },
        {
            "tweet_id": "2021_train_main_tweet_52_comment_71",
            "tweet": "@AUTHOR Depends on whether you are talking about Liberals (Rana/Sagarika etc) or people who believe in liberal values (you). As a Hindu yourself,of course YOU aren't anti-Hindu but the average desi Liberal (capital L) is a hypocritical,snobbish SJW whose core job is outraging on an op-ed"
        },
        {
            "tweet_id": "2021_train_main_tweet_52_comment_72",
            "tweet": "@AUTHOR Haven't you seen @USER 's tweets on hindus @AUTHOR ? 🤔"
        },
        {
            "tweet_id": "2021_train_main_tweet_52_comment_73",
            "tweet": "@AUTHOR Actually in these times they are not liberals they are just hypocrite."
        },
        {
            "tweet_id": "2021_train_main_tweet_52_comment_74",
            "tweet": "@AUTHOR But liberals Hindu kab te🤔🤔"
        },
        {
            "tweet_id": "2021_train_main_tweet_52_comment_75",
            "tweet": "@AUTHOR You are not a liberal.\n\nYou don't agree with all the liberal principles."
        },
        {
            "tweet_id": "2021_train_main_tweet_52_comment_76",
            "tweet": "@AUTHOR To prove yourself liberal and secular you have to be Anti-Hindu! They won't accept you as it is entry criteria to that dumb club."
        },
        {
            "tweet_id": "2021_train_main_tweet_52_comment_77",
            "tweet": "@AUTHOR You're anti-Hindu and non-liberal.\n\nEvidence maang lo bas, flood hon jaayega.",
            "replies": [
                {
                    "tweet_id": "2021_train_main_tweet_52_comment_77_reply_1",
                    "tweet": "@COMMENTATOR @AUTHOR Flood it."
                }
            ]
        },
        {
            "tweet_id": "2021_train_main_tweet_52_comment_78",
            "tweet": "@AUTHOR One finger Madam,liberals are not only anti hindu but anti india as well. However its left libetards we talking about."
        },
        {
            "tweet_id": "2021_train_main_tweet_52_comment_79",
            "tweet": "@AUTHOR ok, but when the cow urine jibes start, it upsets hindu non bjp voters as well."
        },
        {
            "tweet_id": "2021_train_main_tweet_52_comment_80",
            "tweet": "@AUTHOR Indira Gandhi the strongest leader of the Congress party She admired \"Veer Savarkar\" by releasing a postage stamp in 1970.\nLater in 1980 she wrote a letter to Savarkar foundation in which she quoted him as 'Remarkable Son of India\"\n@URL"
        },
        {
            "tweet_id": "2021_train_main_tweet_52_comment_81",
            "tweet": "@AUTHOR विपक्षी पार्टियों और मोदी विरोधियों की एक बात तो सच है..\n\nउनका कहना है तीसरी लहर दूसरी से ज्यादा खतरनाक होगी...\n\nनिश्चित तौर पर \"तीसरी लहर\".. दूसरी से ज्यादा खतरनाक होगी..\n\nदूसरी में 303 सीट आई थीं.. और अब तीसरी में 400 तक पहुंचेंगे.. \n\nइस अनुमान के लिए धन्यवाद सेक्युलरों"
        },
        {
            "tweet_id": "2021_train_main_tweet_52_comment_82",
            "tweet": "@AUTHOR #HinduEcosystem \n\nJoin to replenish your glorious past. \n\nGive a missed call to 8081666000 @URL"
        },
        {
            "tweet_id": "2021_train_main_tweet_52_comment_83",
            "tweet": "@AUTHOR Virus of hate"
        },
        {
            "tweet_id": "2021_train_main_tweet_52_comment_84",
            "tweet": "@AUTHOR How is your FINGURE?\n\nHeard got hurt during shooting."
        },
        {
            "tweet_id": "2021_train_main_tweet_52_comment_85",
            "tweet": "@AUTHOR Can you quotes  one instance when you  liberals came out in the open and said that the hindus were right in a communal conflict?\nSurely in very conflict, it can not be only one community that you hate ,been\n at fault all through the history!"
        },
        {
            "tweet_id": "2021_train_main_tweet_52_comment_86",
            "tweet": "@AUTHOR Liberals are not anti hindu But your behavior is a anti hindu.."
        },
        {
            "tweet_id": "2021_train_main_tweet_52_comment_87",
            "tweet": "@AUTHOR Ok, it seems like \"pakistan is not a terrorist.🤔🤔"
        },
        {
            "tweet_id": "2021_train_main_tweet_52_comment_88",
            "tweet": "@AUTHOR Ban 4g towers 5g towers\nBan AC\nStop Global warming\nBan smoking\nBan deforestation"
        },
        {
            "tweet_id": "2021_train_main_tweet_52_comment_89",
            "tweet": "@AUTHOR Ohho \nThen why they opposed formation of RAM MANDIR."
        },
        {
            "tweet_id": "2021_train_main_tweet_52_comment_90",
            "tweet": "@AUTHOR You can't seem to get peace without 'fingering' all the time! Is it not too much for your pea brain to poke into every matter? \n\nBy the way did you read the CAA 2.5 page document yet? \n\nHow many mohammadans lost Indian citizenship so far since CAA?"
        },
        {
            "tweet_id": "2021_train_main_tweet_52_comment_91",
            "tweet": "@AUTHOR But you are......."
        },
        {
            "tweet_id": "2021_train_main_tweet_52_comment_92",
            "tweet": "@AUTHOR Exactly.\nLiberals are anti India"
        },
        {
            "tweet_id": "2021_train_main_tweet_52_comment_93",
            "tweet": "@AUTHOR मैम आप इन सरे भक्तों को कच्चा खा जाओ"
        },
        {
            "tweet_id": "2021_train_main_tweet_52_comment_94",
            "tweet": "@AUTHOR Yes but u r.. so u r not liberals nor leftist.. u r a hater.. india nd govt hater.. lgi rho beta ji.. next 40 yrs tmhre yhi niklenge.. movie tmse hone s rhi"
        },
        {
            "tweet_id": "2021_train_main_tweet_52_comment_95",
            "tweet": "@AUTHOR Oooohooo definitely they are.\nAachran se saaf saaf dikhta h"
        },
        {
            "tweet_id": "2021_train_main_tweet_52_comment_96",
            "tweet": "@AUTHOR Actually they anti Indian who shed tears for terrorists and spread rumours"
        },
        {
            "tweet_id": "2021_train_main_tweet_52_comment_97",
            "tweet": "@AUTHOR mai, muje sab pataa\n\nmai expert hoo"
        },
        {
            "tweet_id": "2021_train_main_tweet_52_comment_98",
            "tweet": "@AUTHOR just for the namesake you'll are liberals but in actual..you'll the most fanatic, intolerant, hindu phobic and anti democratic."
        },
        {
            "tweet_id": "2021_train_main_tweet_52_comment_99",
            "tweet": "@AUTHOR teri ma ki chut"
        },
        {
            "tweet_id": "2021_train_main_tweet_52_comment_100",
            "tweet": "@AUTHOR True liberals cannot be anti Hindu since by nature only Hinduism is a liberal religion. Those opposing Hinduism are pseudo liberals because they side with regressive ideologies like communism and fundamentalist people."
        },
        {
            "tweet_id": "2021_train_main_tweet_52_comment_101",
            "tweet": "@AUTHOR Liberal are creating eco systems that supports bashing Hinduism in name of secularism. Liberals are trying to cut the roots of Hinduism."
        },
        {
            "tweet_id": "2021_train_main_tweet_52_comment_102",
            "tweet": "@AUTHOR She is anti- hindu anti-india. She also part of tukdey tukdey gang."
        },
        {
            "tweet_id": "2021_train_main_tweet_52_comment_103",
            "tweet": "@AUTHOR Stop promoting tukdey tukdey gang. If you want money we all hindus collect money give to u .promote about kishmir hindus genocide, sikhs genocide done by cong party.bengal genocide by tmc, gujrat train burned by jihadiis mindset more than 50 hindus killed. Promote this."
        },
        {
            "tweet_id": "2021_train_main_tweet_52_comment_104",
            "tweet": "@AUTHOR Swara vaskkeer.... can you answer what's the full form of \"CAA\"....but plz..... without searching the Google, ha..."
        },
        {
            "tweet_id": "2021_train_main_tweet_52_comment_105",
            "tweet": "@AUTHOR But you people are indeed!"
        },
        {
            "tweet_id": "2021_train_main_tweet_52_comment_106",
            "tweet": "@AUTHOR हिन्दू होकर भी कुछ लोग कलंकित है"
        },
        {
            "tweet_id": "2021_train_main_tweet_52_comment_107",
            "tweet": "@AUTHOR Liberals are not anti Hindu same as Rahul Gandhi is a Hindu 😂😂😁😁"
        },
        {
            "tweet_id": "2021_train_main_tweet_52_comment_108",
            "tweet": "@AUTHOR अरे बढ़िया औरत शादी कर लो 44 साल हो गर्ई हो कब तक कुंवारी रहोगी"
        },
        {
            "tweet_id": "2021_train_main_tweet_52_comment_109",
            "tweet": "@AUTHOR शूर्पणखा के बाद कलयुग की एकमात्र कलंकित स्त्री...अब और कुछ कहने को ना रहा"
        },
        {
            "tweet_id": "2021_train_main_tweet_52_comment_110",
            "tweet": "@AUTHOR Tu \"anti hindu\" hai tujhe pta nhi hai par tu hai"
        },
        {
            "tweet_id": "2021_train_main_tweet_52_comment_111",
            "tweet": "@AUTHOR Are you trying to fool yourself this time?"
        },
        {
            "tweet_id": "2021_train_main_tweet_52_comment_112",
            "tweet": "@AUTHOR Liberals never asked for state  citizenship of Hindus who left Pakistan after partition done by Nehru What a tragedy for Hindus they were Indian citizens but not state citizens Shame on fake liberals"
        },
        {
            "tweet_id": "2021_train_main_tweet_52_comment_113",
            "tweet": "@AUTHOR Aap chuitya aurat hain bc"
        },
        {
            "tweet_id": "2021_train_main_tweet_52_comment_114",
            "tweet": "@AUTHOR Kis gadhe ne kaha yeh \nYou're the one"
        },
        {
            "tweet_id": "2021_train_main_tweet_52_comment_115",
            "tweet": "@AUTHOR Tum khud apne dharm ka qabr khodne wali dogli librandu ho @URL"
        },
        {
            "tweet_id": "2021_train_main_tweet_52_comment_116",
            "tweet": "@AUTHOR Every so called fake liberals are anti-hindu n u 4 one of dem"
        },
        {
            "tweet_id": "2021_train_main_tweet_52_comment_117",
            "tweet": "@AUTHOR You are just anti Modi. If Modi did something nice for Mu$|!ms then you won’t like it. Just like you don’t like 3 talaq"
        },
        {
            "tweet_id": "2021_train_main_tweet_52_comment_118",
            "tweet": "@AUTHOR Yes you are.... You didn't tweet against any muslim if any rape happens in mosque like recent case...."
        },
        {
            "tweet_id": "2021_train_main_tweet_52_comment_119",
            "tweet": "@AUTHOR कृपया हमे 10,000 रूपये सिविल सेवा कि तैयारी हेतु किताबों के लिए प्रत्येक व्यक्ति 10 रूपये हेल्प करने की कृपा करे Paytm -: 7004630345@USER  @USER @USER @USER @USER @USER @USER @USER #coronavirus #cancelboardexam #Video",
            "replies": [
                {
                    "tweet_id": "2021_train_main_tweet_52_comment_119_reply_1",
                    "tweet": "@COMMENTATOR @AUTHOR @USER @USER @USER @USER @USER @USER @USER Hair transplant karana hai..dr ne 1 lac ka kharcha bataya hai..please help.."
                }
            ]
        },
        {
            "tweet_id": "2021_train_main_tweet_52_comment_120",
            "tweet": "@AUTHOR Liberals are a confused lot.They have Stockholm syndrome."
        },
        {
            "tweet_id": "2021_train_main_tweet_52_comment_121",
            "tweet": "@AUTHOR Dear Madam  Since 9 11 about 40 000 terror attacks have happened globally of which 39 000 have been done by members of \"peaceful community\" On the other hand Kashmir Hindus though ethnically cleansed have not indulged in any violence please give your \"secular\" view on the matter"
        },
        {
            "tweet_id": "2021_train_main_tweet_52_comment_122",
            "tweet": "@AUTHOR Bas kr andhnamazi 🙏"
        },
        {
            "tweet_id": "2021_train_main_tweet_52_comment_123",
            "tweet": "@AUTHOR All liberals are anti-hindu, Hindus KO mullo se dar yaa fark Nahi padta, tum Jese librandus as hi fark padta hai,"
        },
        {
            "tweet_id": "2021_train_main_tweet_52_comment_124",
            "tweet": "@AUTHOR You are really bloody baster mother fucker lady who always likes to suck Muslim religion."
        },
        {
            "tweet_id": "2021_train_main_tweet_52_comment_125",
            "tweet": "@AUTHOR Tu to liberal bhi hain or anti hindu bhi 😀"
        },
        {
            "tweet_id": "2021_train_main_tweet_52_comment_126",
            "tweet": "@AUTHOR Liberals are irresponsible,  clueless mindless, brainless, a$$holes!"
        },
        {
            "tweet_id": "2021_train_main_tweet_52_comment_127",
            "tweet": "@AUTHOR Jisko aap liberal bata rahi ho including u, unko liberandu kahte hain, jinko har us cheez se problem jisme desh hit ho. Chahe wo caa/nrc/370 article ki baat ho.\nAsli problem ye hai desh hit k bare me koi bhi government kaise soch sakti hai , aur librandu ladte v inke liye 👇 @URL"
        },
        {
            "tweet_id": "2021_train_main_tweet_52_comment_128",
            "tweet": "@AUTHOR You definately are AntiHindu, but more then that, you are Definately a sworn AntiIndia. Theres no question about that."
        }
    ]
}