{
    "tweet_id": "2022_train_main_tweet_119",
    "tweet": "Taliban has nothing to do with Islam but criticizing Taliban is #Islamophobia.",
    "comments": [
        {
            "tweet_id": "2022_train_main_tweet_119_comment_1",
            "tweet": "@AUTHOR Talk about vir das bro",
            "replies": [
                {
                    "tweet_id": "2022_train_main_tweet_119_comment_1_reply_1",
                    "tweet": "@COMMENTATOR @AUTHOR Kutte pe dhyan mat diya kro."
                }
            ]
        },
        {
            "tweet_id": "2022_train_main_tweet_119_comment_2",
            "tweet": "@AUTHOR Prophet Muhammad SAW will participate in Ghazwa e Hind. How this is possible because in Quran the words او مات are used for respected Prophet Muhammad ﷺ And Hazrat Abu Bakar Siddique was the first who announced that respected Prophet Muhammad ﷺ is dead @URL",
            "replies": [
                {
                    "tweet_id": "2022_train_main_tweet_119_comment_2_reply_1",
                    "tweet": "@COMMENTATOR @AUTHOR Kangladeshi black bhikaris🤣\nWaiting for you"
                }
            ]
        }
    ]
}