{
    "tweet_id": "2022_train_main_tweet_150",
    "tweet": "#babrimasjid\n#BabriMasjid was and always will be a mosque.Recently #HagiaSophia and #Azerbaijan mosques ЁЯХМ are a great example.INSHA ALLAH The day will definitely come on which the voice of Azan will also be heard in the BabriMasjid.#BabriMasjidAwaitsJustice \n #6decemberBlackDay @URL",
    "comments": [
        {
            "tweet_id": "2022_train_main_tweet_150_comment_1",
            "tweet": "@AUTHOR Panture thodi banana h itne confidence se bol rhe ho ЁЯШВЁЯШВЁЯШВ",
            "replies": [
                {
                    "tweet_id": "2022_train_main_tweet_150_comment_1_reply_1",
                    "tweet": "@COMMENTATOR @AUTHOR ЁЯдгЁЯдгЁЯдг"
                },
                {
                    "tweet_id": "2022_train_main_tweet_150_comment_1_reply_2",
                    "tweet": "@COMMENTATOR @AUTHOR Are inki adat h dusro ki chiz p kabza karna dekhne do khwab"
                }
            ]
        },
        {
            "tweet_id": "2022_train_main_tweet_150_comment_2",
            "tweet": "@AUTHOR ╪и╪з╪и╪▒█М ┘Е╪│╪м╪п ┌й█Т ┘И╪з┘╛╪│█М ╪к┌й ╪м╪п┘И ╪м█Б╪п ╪м╪з╪▒█М",
            "replies": [
                {
                    "tweet_id": "2022_train_main_tweet_150_comment_2_reply_1",
                    "tweet": "@COMMENTATOR @AUTHOR ╪в┘╛ ┌й█Т ╪о┘И╪з╪и┘И┌║ ┘Е█М┌║ ╪╡╪▒┘Б ╪з┘Ж╪┤╪з╪б ╪з┘Д┘Д█Б"
                }
            ]
        },
        {
            "tweet_id": "2022_train_main_tweet_150_comment_3",
            "tweet": "@AUTHOR рдпреЗ рдлреЛрдЯреЛ рдХрд╛рд╢реА рдХрд╛ рд╣реИ ,,рддреВ рд╣реА рдмрддрд╛ рдореЗрд░реЗ рднрд╛рдИ,,рдорд╕реНрдЬрд┐рдж рдХреА рдЖрдзрд╛рд░рд╢рд┐рд▓рд╛ рдХрд┐рд╕ рдЪреАрдЬ рдкрд░ рдЯрд┐рдХреА рд╣реБрдИ рд╣реИ,рдмрдбрд╝рд╛ рдХрд╛рдиреВрди рдЖрддрд╛ рд╣реИ рди рддреЛ рдмрддрд╛ рджреЗ рднрд╛рдИ ! рдРрд╕рд╛ рд╣рд░ рд╣рд┐рдиреНрджреВ рдордВрджрд┐рд░ рдХреЗ рд╕рд╛рде рд╣реБрдЖ рд╣реИ,рдмрддрд╛ рд╣рдо рдХреНрд╖рдорд╛ рдХрд░реЗ ? рднрд╛рдИрдЪрд╛рд░рд╛ рдХрд╛рдпрдо рдХрд░реЗ? рд╣рд┐рдкреЛрдХреНрд░реЗрд╕реА рдХрдм рддрдХ ред @URL",
            "replies": [
                {
                    "tweet_id": "2022_train_main_tweet_150_comment_3_reply_1",
                    "tweet": "@COMMENTATOR @AUTHOR They will not open their mouth now"
                }
            ]
        },
        {
            "tweet_id": "2022_train_main_tweet_150_comment_4",
            "tweet": "@AUTHOR Allah ki marji ke bina patta tak nahi hilta \nKeep faith in allah",
            "replies": [
                {
                    "tweet_id": "2022_train_main_tweet_150_comment_4_reply_1",
                    "tweet": "@COMMENTATOR @AUTHOR Toh shayad Masjid bhi Ola ke he marji se todi rahegi. Thoda sabr rakho Ola ke marji mutabik sab Mandir wapis ayenge."
                }
            ]
        }
    ]
}